dothdns/__init__.py
dothdns/cli.py
dothdns/config.py
dothdns/helpers.py
dothdns/utils.py
dothdns/version.py
dothdns/commands/__init__.py
dothdns/commands/cmd_class.py
dothdns/commands/main.py
dothdns/commands/config/__init__.py
dothdns/commands/config/command.py
dothdns/commands/config/utils.py
dothdns/commands/down/__init__.py
dothdns/commands/down/command.py
dothdns/commands/images/__init__.py
dothdns/commands/images/command.py
dothdns/commands/images/utils.py
dothdns/commands/init/__init__.py
dothdns/commands/init/command.py
dothdns/commands/init/utils.py
dothdns/commands/run/__init__.py
dothdns/commands/run/command.py
dothdns/commands/run/utils.py
dothdns/commands/update/__init__.py
dothdns/commands/update/command.py
dothdns/container_configs/container_configs.py
dothdns/container_configs/certificates/README.md
dothdns/container_configs/doh-docker/.dockerignore
dothdns/container_configs/doh-docker/Dockerfile
dothdns/container_configs/doh-docker/configs/doh-server.conf
dothdns/container_configs/pihole-docker/configs/resolv.conf
dothdns/container_configs/pihole-docker/configs/dnsmasq.d/.keep
dothdns/container_configs/pihole-docker/configs/pihole/dhcp.leases
dothdns/container_configs/pihole-docker/configs/pihole/pihole-FTL.conf
dothdns/container_configs/pihole-docker/s6_scripts/cont-init.d/01-conf-dnsmasq.sh
dothdns/container_configs/pihole-docker/s6_scripts/cont-init.d/21-conf-dns.sh
dothdns/container_configs/pihole-docker/s6_scripts/fix-attrs.d/02-chown-pihole-configs
dothdns/container_configs/traefik-docker/configs/traefik.toml
dothdns/container_configs/traefik-docker/configs/traefik.conf.d/https_redirect.toml
dothdns/container_configs/traefik-docker/configs/traefik.conf.d/middleware.toml
dothdns/container_configs/traefik-docker/configs/traefik.conf.d/tls.toml
dothdns/container_configs/traefik-docker/shared/README.md
dothdns/container_configs/unbound-docker/unbound.sh
dothdns/container_configs/unbound-docker/configs/unbound.conf
DoTH_DNS-7.0.0.dist-info/LICENSE.rst
DoTH_DNS-7.0.0.dist-info/METADATA
DoTH_DNS-7.0.0.dist-info/WHEEL
DoTH_DNS-7.0.0.dist-info/entry_points.txt
DoTH_DNS-7.0.0.dist-info/top_level.txt
DoTH_DNS-7.0.0.dist-info/RECORD
