Metadata-Version: 2.1
Name: DoTH-DNS
Version: 7.0.0
Summary: DoTH-DNS gives you great control over your DNS traffic
Home-page: https://github.com/Cielquan/DoTH-DNS
Author: Christian Riedel
Maintainer: Christian Riedel
Maintainer-email: cielquan@protonmail.com
License: GPL-3.0
Project-URL: Source, https://github.com/Cielquan/DoTH-DNS
Project-URL: Documentation, https://doth-dns.readthedocs.io/
Project-URL: Tracker, https://github.com/Cielquan/DoTH-DNS/issues
Keywords: DNS,docker,pi-hole,unbound,doh,dot,traefik
Platform: Linux
Classifier: Development Status :: 5 - Production/Stable
Classifier: Environment :: Console
Classifier: Intended Audience :: End Users/Desktop
Classifier: Intended Audience :: System Administrators
Classifier: License :: OSI Approved :: GNU General Public License v3 (GPLv3)
Classifier: Natural Language :: English
Classifier: Operating System :: POSIX :: Linux
Classifier: Programming Language :: Python
Classifier: Programming Language :: Python :: 3
Classifier: Programming Language :: Python :: 3 :: Only
Classifier: Programming Language :: Python :: 3.6
Classifier: Programming Language :: Python :: 3.7
Classifier: Programming Language :: Python :: 3.8
Classifier: Programming Language :: Python :: Implementation :: CPython
Classifier: Topic :: Internet :: Name Service (DNS)
Classifier: Topic :: Security
Classifier: Topic :: Security :: Cryptography
Classifier: Topic :: System :: Networking
Classifier: Topic :: System :: Networking :: Monitoring
Requires-Python: ~=3.6
Requires-Dist: click (<8,>=7)
Requires-Dist: docker (<5,>=4.2.0)
Requires-Dist: requests (<3,>=2)
Requires-Dist: tzlocal (<3,>=2)
Provides-Extra: docs
Requires-Dist: sphinx (<3,>=2.0) ; extra == 'docs'
Requires-Dist: sphinx-click (<3,>=2.3) ; extra == 'docs'
Requires-Dist: sphinx-rtd-theme (>=0.4) ; extra == 'docs'
Provides-Extra: testing
Requires-Dist: pytest (<6,>=5.0) ; extra == 'testing'
Requires-Dist: pytest-cov (<3,>=2.5) ; extra == 'testing'
Requires-Dist: pytest-mock (<3,>=2.0) ; extra == 'testing'
Requires-Dist: pytest-xdist (<2,>=1.31) ; extra == 'testing'
